test_py_package_mana/__init__.py
test_py_package_mana/main.py
test_py_package_mana-0.1.0.dist-info/METADATA
test_py_package_mana-0.1.0.dist-info/WHEEL
test_py_package_mana-0.1.0.dist-info/RECORD
