Metadata-Version: 2.1
Name: test_py_package_mana
Version: 0.1.0
Summary: 
Author: hitpoint6
Author-email: hitpoint6@gmail.com
Requires-Python: >=3.10,<4.0
Classifier: Programming Language :: Python :: 3
Classifier: Programming Language :: Python :: 3.10
Classifier: Programming Language :: Python :: 3.11
Classifier: Programming Language :: Python :: 3.12
Requires-Dist: requests (>=2.32.3,<3.0.0)
